clvlib/__init__.py
clvlib/numpy/__init__.py
clvlib/numpy/angles.py
clvlib/numpy/api.py
clvlib/numpy/clv.py
clvlib/numpy/icle.py
clvlib/numpy/integrators.py
clvlib/numpy/steppers.py
clvlib/pytorch/__init__.py
clvlib/pytorch/angles.py
clvlib/pytorch/api.py
clvlib/pytorch/clv.py
clvlib/pytorch/icle.py
clvlib/pytorch/integrators.py
clvlib/pytorch/steppers.py
clvlib-0.1.1.dist-info/licenses/LICENSE
clvlib-0.1.1.dist-info/METADATA
clvlib-0.1.1.dist-info/WHEEL
clvlib-0.1.1.dist-info/top_level.txt
clvlib-0.1.1.dist-info/RECORD
