Metadata-Version: 2.4
Name: clvlib
Version: 0.1.1
Summary: Lyapunov exponents and Covariant Lyapunov Vectors utilities
Author: Riccardo Consonni
License: MIT License
Project-URL: Homepage, https://github.com/riccardo-consonni/clvlib
Project-URL: Repository, https://github.com/riccardo-consonni/clvlib
Project-URL: Issues, https://github.com/riccardo-consonni/clvlib/issues
Classifier: License :: OSI Approved :: MIT License
Requires-Python: >=3.9
License-File: LICENSE
Requires-Dist: numpy>=1.22
Requires-Dist: scipy>=1.8
Requires-Dist: numba>=0.56
Requires-Dist: torch>=1.12
Requires-Dist: tqdm>=4.66
Provides-Extra: dev
Requires-Dist: pytest>=7; extra == "dev"
Requires-Dist: ruff>=0.5; extra == "dev"
Requires-Dist: mypy>=1.10; extra == "dev"
Dynamic: license-file
